MANIFEST.in
README.txt
setup.cfg
setup.py
beyondskins/__init__.py
beyondskins.pyconbrasil2008.egg-info/PKG-INFO
beyondskins.pyconbrasil2008.egg-info/SOURCES.txt
beyondskins.pyconbrasil2008.egg-info/dependency_links.txt
beyondskins.pyconbrasil2008.egg-info/entry_points.txt
beyondskins.pyconbrasil2008.egg-info/namespace_packages.txt
beyondskins.pyconbrasil2008.egg-info/not-zip-safe
beyondskins.pyconbrasil2008.egg-info/requires.txt
beyondskins.pyconbrasil2008.egg-info/top_level.txt
beyondskins/pyconbrasil2008/README.txt
beyondskins/pyconbrasil2008/__init__.py
beyondskins/pyconbrasil2008/config.py
beyondskins/pyconbrasil2008/configure.zcml
beyondskins/pyconbrasil2008/profiles.zcml
beyondskins/pyconbrasil2008/setuphandlers.py
beyondskins/pyconbrasil2008/tests.py
beyondskins/pyconbrasil2008/version.txt
beyondskins/pyconbrasil2008/Extensions/Install.py
beyondskins/pyconbrasil2008/Extensions/__init__.py
beyondskins/pyconbrasil2008/profiles/default/cssregistry.xml
beyondskins/pyconbrasil2008/profiles/default/import_steps.xml
beyondskins/pyconbrasil2008/profiles/default/jsregistry.xml
beyondskins/pyconbrasil2008/profiles/default/metadata.xml
beyondskins/pyconbrasil2008/profiles/default/skins.xml
beyondskins/pyconbrasil2008/skins/pyconbrasil2008_custom_images/CONTENT.txt
beyondskins/pyconbrasil2008/skins/pyconbrasil2008_custom_images/arrowLeft.gif
beyondskins/pyconbrasil2008/skins/pyconbrasil2008_custom_images/arrowRight.gif
beyondskins/pyconbrasil2008/skins/pyconbrasil2008_custom_images/favicon.ico
beyondskins/pyconbrasil2008/skins/pyconbrasil2008_custom_images/rss.gif
beyondskins/pyconbrasil2008/skins/pyconbrasil2008_custom_styles/CONTENT.txt
beyondskins/pyconbrasil2008/skins/pyconbrasil2008_custom_styles/base_properties.props
beyondskins/pyconbrasil2008/skins/pyconbrasil2008_custom_styles/print.css.dtml
beyondskins/pyconbrasil2008/skins/pyconbrasil2008_custom_templates/CONTENT.txt
beyondskins/pyconbrasil2008/skins/pyconbrasil2008_custom_templates/footer.pt
beyondskins/pyconbrasil2008/skins/pyconbrasil2008_custom_templates/main_template.pt
beyondskins/pyconbrasil2008/skins/pyconbrasil2008_custom_templates/portlet_news.pt
beyondskins/pyconbrasil2008/skins/pyconbrasil2008_images/CONTENT.txt
beyondskins/pyconbrasil2008/skins/pyconbrasil2008_images/background.gif
beyondskins/pyconbrasil2008/skins/pyconbrasil2008_images/banner.jpg
