Metadata-Version: 1.0
Name: beyondskins.pyconbrasil2008
Version: 1.0
Summary: Plone Theme developed by Simples Consultoria
Home-page: http://www.simplesconsultoria.com.br/
Author: Simples Consultoria
Author-email: contato@simplesconsultoria.com.br
License: GPL
Keywords: web zope plone theme skin simples_consultoria plone25
Platform: UNKNOWN
Classifier: Framework :: Plone
Classifier: Framework :: Zope2
Classifier: Framework :: Zope3
Classifier: Programming Language :: Python
Classifier: Topic :: Software Development :: Libraries :: Python Modules
